setup.cfg
setup.py
file_mas/_init_.py
file_mas/test.py
file_mas.egg-info/PKG-INFO
file_mas.egg-info/SOURCES.txt
file_mas.egg-info/dependency_links.txt
file_mas.egg-info/not-zip-safe
file_mas.egg-info/top_level.txt