Metadata-Version: 2.1
Name: file-mas
Version: 0.0
Summary: array that saves in file
Home-page: UNKNOWN
Author-email: anton2019artiukhov@yandex.ru
License: UNKNOWN
Platform: UNKNOWN
